yahfin/__init__.py
yahfin/engines.py
yahfin/functions.py
yahfin/utils.py
yahfin/yahfin.py
yahfin-0.3.6.dist-info/LICENSE
yahfin-0.3.6.dist-info/METADATA
yahfin-0.3.6.dist-info/WHEEL
yahfin-0.3.6.dist-info/top_level.txt
yahfin-0.3.6.dist-info/RECORD
