Metadata-Version: 2.1
Name: yahfin
Version: 0.3.6
Summary: Yahoo Finance Python Wrapper (Unofficial)
Home-page: https://github.com/theonlyanil/yahfin
Author: Anil Sardiwal
Author-email: theonlyanil@gmail.com
License: UNKNOWN
Platform: UNKNOWN
Classifier: Programming Language :: Python :: 3
Classifier: License :: OSI Approved :: MIT License
Classifier: Intended Audience :: Financial and Insurance Industry
Classifier: Intended Audience :: Developers
Classifier: Intended Audience :: Science/Research
Classifier: Topic :: Scientific/Engineering :: Information Analysis
Classifier: Topic :: Software Development :: Libraries
Classifier: Topic :: Software Development :: Libraries :: Python Modules
Requires-Python: >=3.7.7
